{
    "global": {
        "check_for_updates_on_startup": true,
        "show_in_menu_bar": true,
        "show_profile_name_in_menu_bar": false
    },
    "profiles": [
        {
            "complex_modifications": {
                "rules": [
                    {
                        "description": "Change caps_lock to f20 (hyper key) and set hyper_modifier or esc if pressed alone",
                        "manipulators": [
                            {
                                "from": {
                                    "key_code": "caps_lock",
                                    "modifiers": {
                                        "optional": [
                                            "any"
                                        ]
                                    }
                                },
                                "to": [
                                    {
                                        "set_variable": {
                                            "name": "hyper_modifier",
                                            "value": 1
                                        }
                                    },
                                    {
                                        "key_code": "f20"
                                    }
                                ],
                                "to_after_key_up": [
                                    {
                                        "set_variable": {
                                            "name": "hyper_modifier",
                                            "value": 0
                                        }
                                    }
                                ],
                                "to_if_alone": [
                                    {
                                        "key_code": "escape"
                                    }
                                ],
                                "type": "basic"
                            }
                        ]
                    },
                    {
                        "description": "Change both shifts together to caps_lock",
                        "manipulators": [
                            {
                                "from": {
                                    "key_code": "left_shift",
                                    "modifiers": {
                                        "mandatory": [
                                            "right_shift"
                                        ],
                                        "optional": [
                                            "caps_lock"
                                        ]
                                    }
                                },
                                "to": [
                                    {
                                        "key_code": "caps_lock"
                                    }
                                ],
                                "type": "basic"
                            },
                            {
                                "from": {
                                    "key_code": "right_shift",
                                    "modifiers": {
                                        "mandatory": [
                                            "left_shift"
                                        ],
                                        "optional": [
                                            "caps_lock"
                                        ]
                                    }
                                },
                                "to": [
                                    {
                                        "key_code": "caps_lock"
                                    }
                                ],
                                "type": "basic"
                            }
                        ]
                    },
                    {
                        "description": "Change alt space (nonbreaking space) to space",
                        "manipulators": [
                            {
                                "from": {
                                    "key_code": "spacebar",
                                    "modifiers": {
                                        "mandatory": [
                                            "option"
                                        ]
                                    }
                                },
                                "to": [
                                    {
                                        "key_code": "spacebar"
                                    }
                                ],
                                "type": "basic"
                            }
                        ]
                    }
                ]
            },
            "name": "Default profile",
            "selected": true,
            "simple_modifications": [
                {
                    "from": {
                        "key_code": "right_command"
                    },
                    "to": {
                        "key_code": "right_control"
                    }
                }
            ]
        }
    ]
}
